[
    {
        "title": "DOGE's Only Public Ledger Is Riddled with Mistakes",
        "link": "https:/www.nytimes.com/2025/02/21/upshot/doge-musk-trump-errors.html"
    },
    {
        "title": "Apple pulls data protection tool after UK government security row",
        "link": "https:/www.bbc.com/news/articles/cgj54eq4vejo"
    },
    {
        "title": "Money lessons without money: The financial literacy fallacy",
        "link": "https:/anandsanwal.me/financial-literacy-fallacy/"
    },
    {
        "title": "These years in Common Lisp: 2023-2024 in review",
        "link": "https:/lisp-journey.gitlab.io/blog/these-years-in-common-lisp-2023-2024-in-review/"
    },
    {
        "title": "A vending machine, on the internet",
        "link": "https:/threekindwords.com/blog/vending-machine-on-the-internet/"
    },
    {
        "title": "Why Ruby on Rails still matters",
        "link": "https:/www.contraption.co/rails-versus-nextjs/"
    },
    {
        "title": "Surface-Stable Fractal Dither on Playdate",
        "link": "https:/aras-p.info/blog/2025/02/09/Surface-Stable-Fractal-Dither-on-Playdate/"
    },
    {
        "title": "Bybit loses $1.5B in hack but can cover loss, CEO confirms",
        "link": "https:/www.tradingview.com/news/coindesk:cda1c390e094b:0-bybit-ceo-confirms-exchange-was-hacked-for-1-46b-says-his-firm-can-cover-the-loss/"
    },
    {
        "title": "Johnny.Decimal \u2013 A system to organise your life",
        "link": "https:/johnnydecimal.com"
    },
    {
        "title": "Where are all the Rewrite Rules?",
        "link": "https:/www.philipzucker.com/rewrite_rules/"
    },
    {
        "title": "Yocto, RockPi and SBOMs: Building modern embedded Linux images",
        "link": "https:/vpetersson.com/2025/02/21/yocto-rockpi-and-sboms.html"
    },
    {
        "title": "The Ren'Py Visual Novel Engine",
        "link": "https:/www.renpy.org/"
    },
    {
        "title": "DeepDive in everything of Llama3: revealing detailed insights and implementation",
        "link": "https:/github.com/therealoliver/Deepdive-llama3-from-scratch"
    },
    {
        "title": "Show HN: Slime OS \u2013 An open-source app launcher for RP2040 based devices",
        "link": "https:/github.com/abeisgoat/slime_os"
    },
    {
        "title": "Sparse Voxels Rasterization: Real-Time High-Fidelity Radiance Field Rendering",
        "link": "https:/svraster.github.io/"
    },
    {
        "title": "I found a backdoor into my bed",
        "link": "https:/trufflesecurity.com/blog/removing-jeff-bezos-from-my-bed"
    },
    {
        "title": "SVDQuant+NVFP4: 4\u00d7 Smaller, 3\u00d7 Faster FLUX with 16-bit Quality on Blackwell GPUs",
        "link": "https:/hanlab.mit.edu/blog/svdquant-nvfp4"
    },
    {
        "title": "Suckless.org: software that sucks less",
        "link": "https:/suckless.org/"
    },
    {
        "title": "Twitch's new storage limits will purge swaths of Internet gaming history",
        "link": "https:/arstechnica.com/gaming/2025/02/history-evaporating-before-our-eyes-gamers-lament-twitchs-new-video-storage-limits/"
    },
    {
        "title": "Fly To Podman: a script that will help you to migrate from Docker",
        "link": "https:/github.com/Edu4rdSHL/fly-to-podman"
    },
    {
        "title": "20 years working on the same software product",
        "link": "https:/successfulsoftware.net/2025/02/21/20-years-working-on-the-same-software-product/"
    }
]